window_input/__init__.py
window_input-1.7.dist-info/LICENSE
window_input-1.7.dist-info/METADATA
window_input-1.7.dist-info/WHEEL
window_input-1.7.dist-info/top_level.txt
window_input-1.7.dist-info/RECORD
