Metadata-Version: 2.1
Name: window-input
Version: 1.7
Summary: A set of tools for interacting with windows regardless of them being minimized or in background.
Home-page: https://github.com/56kyle/window_input
Author: Kyle Oliver
Author-email: 56kyleoliver@gmail.com
License: UNKNOWN
Platform: UNKNOWN
Classifier: Programming Language :: Python :: 3
Classifier: License :: OSI Approved :: MIT License
Requires-Dist: pywin32
Requires-Dist: Pillow
